_rpi_ws281x.cpython-37m-arm-linux-gnueabihf.so
rpi_ws281x/__init__.py
rpi_ws281x/rpi_ws281x.py
rpi_ws281x-4.3.4.dist-info/LICENSE
rpi_ws281x-4.3.4.dist-info/METADATA
rpi_ws281x-4.3.4.dist-info/WHEEL
rpi_ws281x-4.3.4.dist-info/top_level.txt
rpi_ws281x-4.3.4.dist-info/RECORD
