Metadata-Version: 1.0
Name: rpi_ws281x
Version: 4.3.4
Summary: Userspace Raspberry Pi PWM/PCM/SPI library for SK6812 and WS281X LEDs.
Home-page: https://github.com/rpi-ws281x/rpi-ws281x-python/
Author: Jeremy Garff <jer@jers.net>, Phil Howard <phil@pimoroni.com>
Author-email: jer@jers.net, phil@pimoroni.com
License: MIT
Platform: UNKNOWN
